xits2/__init__.py
xits2/workspace.py
xits2/v21/__init__.py
xits2/v21/constants.py
xits2/v21/helpers.py
xits2/v21/vocab.py
xits2-0.0.1.dist-info/LICENSE
xits2-0.0.1.dist-info/METADATA
xits2-0.0.1.dist-info/WHEEL
xits2-0.0.1.dist-info/top_level.txt
xits2-0.0.1.dist-info/RECORD
