Metadata-Version: 2.1
Name: xits2
Version: 0.0.1
Home-page: http://github.com/opensticks/xits2
Author: Tomás Lima, Adrian Dinis
Author-email: tomas@abusetotal.com, adrian@abusetotal.com
Requires-Python: >=3.6
License-File: LICENSE
Requires-Dist: stix2 >=3.0.1
Provides-Extra: dev
